<mujoco>
    <asset>
        <mesh name="D_243_1" file="objects/D_243/D_243_1.stl"/>
        <mesh name="D_243_2" file="objects/D_243/D_243_2.stl"/>
        <mesh name="D_243_3" file="objects/D_243/D_243_3.stl"/>
        <mesh name="D_243_4" file="objects/D_243/D_243_4.stl"/>
        <mesh name="D_243_5" file="objects/D_243/D_243_5.stl"/>
        <mesh name="D_243_6" file="objects/D_243/D_243_6.stl"/>
        <mesh name="D_243_7" file="objects/D_243/D_243_7.stl"/>
        <mesh name="D_243_8" file="objects/D_243/D_243_8.stl"/>
        <mesh name="D_243_9" file="objects/D_243/D_243_9.stl"/>
        <mesh name="D_243_10" file="objects/D_243/D_243_10.stl"/>
        <mesh name="D_243_11" file="objects/D_243/D_243_11.stl"/>
        <mesh name="D_243_12" file="objects/D_243/D_243_12.stl"/>
        <mesh name="D_243_13" file="objects/D_243/D_243_13.stl"/>
        <mesh name="D_243_14" file="objects/D_243/D_243_14.stl"/>
        <mesh name="D_243_15" file="objects/D_243/D_243_15.stl"/>
        <mesh name="D_243_16" file="objects/D_243/D_243_16.stl"/>
        <mesh name="D_243_17" file="objects/D_243/D_243_17.stl"/>
        <mesh name="D_243_18" file="objects/D_243/D_243_18.stl"/>
        <mesh name="D_243_19" file="objects/D_243/D_243_19.stl"/>
        <mesh name="D_243_20" file="objects/D_243/D_243_20.stl"/>
        <mesh name="D_243_21" file="objects/D_243/D_243_21.stl"/>
        <mesh name="D_243_22" file="objects/D_243/D_243_22.stl"/>
        <mesh name="D_243_23" file="objects/D_243/D_243_23.stl"/>
        <mesh name="D_243_24" file="objects/D_243/D_243_24.stl"/>
        <mesh name="D_243_25" file="objects/D_243/D_243_25.stl"/>
        <mesh name="D_243_26" file="objects/D_243/D_243_26.stl"/>
        <mesh name="D_243_27" file="objects/D_243/D_243_27.stl"/>
        <mesh name="D_243_28" file="objects/D_243/D_243_28.stl"/>
        <mesh name="D_243_29" file="objects/D_243/D_243_29.stl"/>
        <mesh name="D_243_30" file="objects/D_243/D_243_30.stl"/>
        <mesh name="D_243_31" file="objects/D_243/D_243_31.stl"/>
        <mesh name="D_243_32" file="objects/D_243/D_243_32.stl"/>
        <mesh name="D_243_33" file="objects/D_243/D_243_33.stl"/>
        <mesh name="D_243_34" file="objects/D_243/D_243_34.stl"/>
        <mesh name="D_243_35" file="objects/D_243/D_243_35.stl"/>
        <mesh name="D_243_36" file="objects/D_243/D_243_36.stl"/>
        <mesh name="D_243_37" file="objects/D_243/D_243_37.stl"/>
        <mesh name="D_243_38" file="objects/D_243/D_243_38.stl"/>
        <mesh name="D_243_39" file="objects/D_243/D_243_39.stl"/>
        <mesh name="D_243_40" file="objects/D_243/D_243_40.stl"/>
        <mesh name="D_243_41" file="objects/D_243/D_243_41.stl"/>
        <mesh name="D_243_42" file="objects/D_243/D_243_42.stl"/>
        <mesh name="D_243_43" file="objects/D_243/D_243_43.stl"/>
        <mesh name="D_243_44" file="objects/D_243/D_243_44.stl"/>
        <mesh name="D_243_45" file="objects/D_243/D_243_45.stl"/>
        <mesh name="D_243_46" file="objects/D_243/D_243_46.stl"/>
        <mesh name="D_243_47" file="objects/D_243/D_243_47.stl"/>
        <mesh name="D_243_48" file="objects/D_243/D_243_48.stl"/>
        <mesh name="D_243_49" file="objects/D_243/D_243_49.stl"/>
        <mesh name="D_243_50" file="objects/D_243/D_243_50.stl"/>
        <mesh name="D_243_51" file="objects/D_243/D_243_51.stl"/>
        <mesh name="D_243_52" file="objects/D_243/D_243_52.stl"/>
        <mesh name="D_243_53" file="objects/D_243/D_243_53.stl"/>
        <mesh name="D_243_54" file="objects/D_243/D_243_54.stl"/>
        <mesh name="D_243_55" file="objects/D_243/D_243_55.stl"/>
        <mesh name="D_243_56" file="objects/D_243/D_243_56.stl"/>
        <mesh name="D_243_57" file="objects/D_243/D_243_57.stl"/>
        <mesh name="D_243_58" file="objects/D_243/D_243_58.stl"/>
        <mesh name="D_243_59" file="objects/D_243/D_243_59.stl"/>
        <mesh name="D_243_60" file="objects/D_243/D_243_60.stl"/>
        <mesh name="D_243_61" file="objects/D_243/D_243_61.stl"/>
        <mesh name="D_243_62" file="objects/D_243/D_243_62.stl"/>
        <mesh name="D_243_63" file="objects/D_243/D_243_63.stl"/>
        <mesh name="D_243_64" file="objects/D_243/D_243_64.stl"/>
        <mesh name="D_243_65" file="objects/D_243/D_243_65.stl"/>
        <mesh name="D_243_66" file="objects/D_243/D_243_66.stl"/>
        <mesh name="D_243_67" file="objects/D_243/D_243_67.stl"/>
        <mesh name="D_243_68" file="objects/D_243/D_243_68.stl"/>
        <mesh name="D_243_69" file="objects/D_243/D_243_69.stl"/>
        <mesh name="D_243_70" file="objects/D_243/D_243_70.stl"/>
        <mesh name="D_243_71" file="objects/D_243/D_243_71.stl"/>
        <mesh name="D_243_72" file="objects/D_243/D_243_72.stl"/>
        <mesh name="D_243_73" file="objects/D_243/D_243_73.stl"/>
        <mesh name="D_243_74" file="objects/D_243/D_243_74.stl"/>
        <mesh name="D_243_75" file="objects/D_243/D_243_75.stl"/>
        <mesh name="D_243_76" file="objects/D_243/D_243_76.stl"/>
        <mesh name="D_243_77" file="objects/D_243/D_243_77.stl"/>
        <mesh name="D_243_visual" file="objects/D_243/D_243_full.stl"/>
    </asset>
</mujoco>