<mujoco>
    <worldbody>
        <body name="object" pos="0 0 0" euler="">
            <geom type="mesh" group="1" mesh="D_254_1" condim="6" density="" friction="" solimp="0.99 0.999 0.001" margin="0.0005" solref="0.008 1.0"/>
            <geom type="mesh" group="1" mesh="D_254_2" condim="6" density="" friction="" solimp="0.99 0.999 0.001" margin="0.0005" solref="0.008 1.0"/>
            <geom type="mesh" group="1" mesh="D_254_3" condim="6" density="" friction="" solimp="0.99 0.999 0.001" margin="0.0005" solref="0.008 1.0"/>
            <geom type="mesh" group="1" mesh="D_254_4" condim="6" density="" friction="" solimp="0.99 0.999 0.001" margin="0.0005" solref="0.008 1.0"/>
            <geom type="mesh" group="1" mesh="D_254_5" condim="6" density="" friction="" solimp="0.99 0.999 0.001" margin="0.0005" solref="0.008 1.0"/>
            <geom type="mesh" group="1" mesh="D_254_6" condim="6" density="" friction="" solimp="0.99 0.999 0.001" margin="0.0005" solref="0.008 1.0"/>
            <geom type="mesh" group="1" mesh="D_254_7" condim="6" density="" friction="" solimp="0.99 0.999 0.001" margin="0.0005" solref="0.008 1.0"/>
            <geom type="mesh" group="1" mesh="D_254_8" condim="6" density="" friction="" solimp="0.99 0.999 0.001" margin="0.0005" solref="0.008 1.0"/>
            <geom type="mesh" group="1" mesh="D_254_9" condim="6" density="" friction="" solimp="0.99 0.999 0.001" margin="0.0005" solref="0.008 1.0"/>
            <geom type="mesh" group="1" mesh="D_254_10" condim="6" density="" friction="" solimp="0.99 0.999 0.001" margin="0.0005" solref="0.008 1.0"/>
            <geom type="mesh" group="1" mesh="D_254_11" condim="6" density="" friction="" solimp="0.99 0.999 0.001" margin="0.0005" solref="0.008 1.0"/>
            <geom type="mesh" group="1" mesh="D_254_12" condim="6" density="" friction="" solimp="0.99 0.999 0.001" margin="0.0005" solref="0.008 1.0"/>
            <geom type="mesh" group="1" mesh="D_254_13" condim="6" density="" friction="" solimp="0.99 0.999 0.001" margin="0.0005" solref="0.008 1.0"/>
            <geom type="mesh" group="1" mesh="D_254_14" condim="6" density="" friction="" solimp="0.99 0.999 0.001" margin="0.0005" solref="0.008 1.0"/>
            <geom type="mesh" group="1" mesh="D_254_15" condim="6" density="" friction="" solimp="0.99 0.999 0.001" margin="0.0005" solref="0.008 1.0"/>
            <geom type="mesh" group="1" mesh="D_254_16" condim="6" density="" friction="" solimp="0.99 0.999 0.001" margin="0.0005" solref="0.008 1.0"/>
            <geom type="mesh" group="1" mesh="D_254_17" condim="6" density="" friction="" solimp="0.99 0.999 0.001" margin="0.0005" solref="0.008 1.0"/>
            <geom type="mesh" group="1" mesh="D_254_18" condim="6" density="" friction="" solimp="0.99 0.999 0.001" margin="0.0005" solref="0.008 1.0"/>
            <geom type="mesh" group="1" mesh="D_254_19" condim="6" density="" friction="" solimp="0.99 0.999 0.001" margin="0.0005" solref="0.008 1.0"/>
            <geom type="mesh" group="1" mesh="D_254_20" condim="6" density="" friction="" solimp="0.99 0.999 0.001" margin="0.0005" solref="0.008 1.0"/>
            <geom type="mesh" group="1" mesh="D_254_21" condim="6" density="" friction="" solimp="0.99 0.999 0.001" margin="0.0005" solref="0.008 1.0"/>
            <geom type="mesh" group="1" mesh="D_254_22" condim="6" density="" friction="" solimp="0.99 0.999 0.001" margin="0.0005" solref="0.008 1.0"/>
            <geom type="mesh" group="1" mesh="D_254_23" condim="6" density="" friction="" solimp="0.99 0.999 0.001" margin="0.0005" solref="0.008 1.0"/>
            <geom type="mesh" group="1" mesh="D_254_24" condim="6" density="" friction="" solimp="0.99 0.999 0.001" margin="0.0005" solref="0.008 1.0"/>
            <geom type="mesh" group="1" mesh="D_254_25" condim="6" density="" friction="" solimp="0.99 0.999 0.001" margin="0.0005" solref="0.008 1.0"/>
            <geom type="mesh" group="1" mesh="D_254_26" condim="6" density="" friction="" solimp="0.99 0.999 0.001" margin="0.0005" solref="0.008 1.0"/>
            <geom type="mesh" group="1" mesh="D_254_27" condim="6" density="" friction="" solimp="0.99 0.999 0.001" margin="0.0005" solref="0.008 1.0"/>
            <geom type="mesh" group="1" mesh="D_254_28" condim="6" density="" friction="" solimp="0.99 0.999 0.001" margin="0.0005" solref="0.008 1.0"/>
            <geom type="mesh" group="1" mesh="D_254_29" condim="6" density="" friction="" solimp="0.99 0.999 0.001" margin="0.0005" solref="0.008 1.0"/>
            <geom type="mesh" group="1" mesh="D_254_30" condim="6" density="" friction="" solimp="0.99 0.999 0.001" margin="0.0005" solref="0.008 1.0"/>
            <geom type="mesh" group="1" mesh="D_254_31" condim="6" density="" friction="" solimp="0.99 0.999 0.001" margin="0.0005" solref="0.008 1.0"/>
            <geom type="mesh" group="1" mesh="D_254_32" condim="6" density="" friction="" solimp="0.99 0.999 0.001" margin="0.0005" solref="0.008 1.0"/>
            <geom type="mesh" group="1" mesh="D_254_33" condim="6" density="" friction="" solimp="0.99 0.999 0.001" margin="0.0005" solref="0.008 1.0"/>
            <geom type="mesh" group="1" mesh="D_254_34" condim="6" density="" friction="" solimp="0.99 0.999 0.001" margin="0.0005" solref="0.008 1.0"/>
            <geom type="mesh" group="1" mesh="D_254_35" condim="6" density="" friction="" solimp="0.99 0.999 0.001" margin="0.0005" solref="0.008 1.0"/>
            <geom type="mesh" group="1" mesh="D_254_36" condim="6" density="" friction="" solimp="0.99 0.999 0.001" margin="0.0005" solref="0.008 1.0"/>
            <geom type="mesh" group="1" mesh="D_254_37" condim="6" density="" friction="" solimp="0.99 0.999 0.001" margin="0.0005" solref="0.008 1.0"/>
            <geom type="mesh" group="1" mesh="D_254_38" condim="6" density="" friction="" solimp="0.99 0.999 0.001" margin="0.0005" solref="0.008 1.0"/>
            <geom type="mesh" group="1" mesh="D_254_39" condim="6" density="" friction="" solimp="0.99 0.999 0.001" margin="0.0005" solref="0.008 1.0"/>
            <geom type="mesh" group="1" mesh="D_254_40" condim="6" density="" friction="" solimp="0.99 0.999 0.001" margin="0.0005" solref="0.008 1.0"/>
            <geom type="mesh" group="1" mesh="D_254_41" condim="6" density="" friction="" solimp="0.99 0.999 0.001" margin="0.0005" solref="0.008 1.0"/>
            <geom type="mesh" group="1" mesh="D_254_42" condim="6" density="" friction="" solimp="0.99 0.999 0.001" margin="0.0005" solref="0.008 1.0"/>
            <geom type="mesh" group="1" mesh="D_254_43" condim="6" density="" friction="" solimp="0.99 0.999 0.001" margin="0.0005" solref="0.008 1.0"/>
            <geom type="mesh" group="1" mesh="D_254_44" condim="6" density="" friction="" solimp="0.99 0.999 0.001" margin="0.0005" solref="0.008 1.0"/>
            <geom type="mesh" group="1" mesh="D_254_45" condim="6" density="" friction="" solimp="0.99 0.999 0.001" margin="0.0005" solref="0.008 1.0"/>
            <geom type="mesh" group="1" mesh="D_254_46" condim="6" density="" friction="" solimp="0.99 0.999 0.001" margin="0.0005" solref="0.008 1.0"/>
            <geom type="mesh" group="1" mesh="D_254_47" condim="6" density="" friction="" solimp="0.99 0.999 0.001" margin="0.0005" solref="0.008 1.0"/>
            <geom type="mesh" group="1" mesh="D_254_48" condim="6" density="" friction="" solimp="0.99 0.999 0.001" margin="0.0005" solref="0.008 1.0"/>
            <geom type="mesh" group="1" mesh="D_254_49" condim="6" density="" friction="" solimp="0.99 0.999 0.001" margin="0.0005" solref="0.008 1.0"/>
            <geom type="mesh" group="1" mesh="D_254_50" condim="6" density="" friction="" solimp="0.99 0.999 0.001" margin="0.0005" solref="0.008 1.0"/>
            <geom type="mesh" group="1" mesh="D_254_51" condim="6" density="" friction="" solimp="0.99 0.999 0.001" margin="0.0005" solref="0.008 1.0"/>
            <geom type="mesh" group="1" mesh="D_254_52" condim="6" density="" friction="" solimp="0.99 0.999 0.001" margin="0.0005" solref="0.008 1.0"/>
            <geom type="mesh" group="1" mesh="D_254_53" condim="6" density="" friction="" solimp="0.99 0.999 0.001" margin="0.0005" solref="0.008 1.0"/>
            <geom type="mesh" group="1" mesh="D_254_54" condim="6" density="" friction="" solimp="0.99 0.999 0.001" margin="0.0005" solref="0.008 1.0"/>
            <geom type="mesh" group="1" mesh="D_254_55" condim="6" density="" friction="" solimp="0.99 0.999 0.001" margin="0.0005" solref="0.008 1.0"/>
            <geom type="mesh" group="1" mesh="D_254_56" condim="6" density="" friction="" solimp="0.99 0.999 0.001" margin="0.0005" solref="0.008 1.0"/>
            <geom type="mesh" group="1" mesh="D_254_57" condim="6" density="" friction="" solimp="0.99 0.999 0.001" margin="0.0005" solref="0.008 1.0"/>
            <geom type="mesh" group="1" mesh="D_254_58" condim="6" density="" friction="" solimp="0.99 0.999 0.001" margin="0.0005" solref="0.008 1.0"/>
            <geom type="mesh" group="1" mesh="D_254_59" condim="6" density="" friction="" solimp="0.99 0.999 0.001" margin="0.0005" solref="0.008 1.0"/>
            <geom type="mesh" group="1" mesh="D_254_60" condim="6" density="" friction="" solimp="0.99 0.999 0.001" margin="0.0005" solref="0.008 1.0"/>
            <geom type="mesh" group="1" mesh="D_254_61" condim="6" density="" friction="" solimp="0.99 0.999 0.001" margin="0.0005" solref="0.008 1.0"/>
            <geom type="mesh" group="1" mesh="D_254_62" condim="6" density="" friction="" solimp="0.99 0.999 0.001" margin="0.0005" solref="0.008 1.0"/>
            <geom type="mesh" group="1" mesh="D_254_63" condim="6" density="" friction="" solimp="0.99 0.999 0.001" margin="0.0005" solref="0.008 1.0"/>
            <geom type="mesh" group="1" mesh="D_254_64" condim="6" density="" friction="" solimp="0.99 0.999 0.001" margin="0.0005" solref="0.008 1.0"/>
            <geom type="mesh" group="1" mesh="D_254_65" condim="6" density="" friction="" solimp="0.99 0.999 0.001" margin="0.0005" solref="0.008 1.0"/>
            <geom type="mesh" group="1" mesh="D_254_66" condim="6" density="" friction="" solimp="0.99 0.999 0.001" margin="0.0005" solref="0.008 1.0"/>
            <geom type="mesh" group="1" mesh="D_254_67" condim="6" density="" friction="" solimp="0.99 0.999 0.001" margin="0.0005" solref="0.008 1.0"/>
            <geom type="mesh" group="1" mesh="D_254_68" condim="6" density="" friction="" solimp="0.99 0.999 0.001" margin="0.0005" solref="0.008 1.0"/>
            <geom type="mesh" group="1" mesh="D_254_69" condim="6" density="" friction="" solimp="0.99 0.999 0.001" margin="0.0005" solref="0.008 1.0"/>
            <geom type="mesh" group="1" mesh="D_254_70" condim="6" density="" friction="" solimp="0.99 0.999 0.001" margin="0.0005" solref="0.008 1.0"/>
            <geom type="mesh" group="1" mesh="D_254_71" condim="6" density="" friction="" solimp="0.99 0.999 0.001" margin="0.0005" solref="0.008 1.0"/>
            <geom type="mesh" group="1" mesh="D_254_72" condim="6" density="" friction="" solimp="0.99 0.999 0.001" margin="0.0005" solref="0.008 1.0"/>
            <geom type="mesh" group="1" mesh="D_254_73" condim="6" density="" friction="" solimp="0.99 0.999 0.001" margin="0.0005" solref="0.008 1.0"/>
            <geom type="mesh" group="1" mesh="D_254_74" condim="6" density="" friction="" solimp="0.99 0.999 0.001" margin="0.0005" solref="0.008 1.0"/>
            <geom type="mesh" group="1" mesh="D_254_75" condim="6" density="" friction="" solimp="0.99 0.999 0.001" margin="0.0005" solref="0.008 1.0"/>
            <geom type="mesh" group="1" mesh="D_254_76" condim="6" density="" friction="" solimp="0.99 0.999 0.001" margin="0.0005" solref="0.008 1.0"/>
            <geom type="mesh" group="1" mesh="D_254_77" condim="6" density="" friction="" solimp="0.99 0.999 0.001" margin="0.0005" solref="0.008 1.0"/>
            <geom type="mesh" group="1" mesh="D_254_78" condim="6" density="" friction="" solimp="0.99 0.999 0.001" margin="0.0005" solref="0.008 1.0"/>
            <geom type="mesh" group ="2" mass="0" contype="0" rgba="" conaffinity="0" mesh="D_254_visual"/>
            <joint class="free"/>
        </body>
    </worldbody>
</mujoco>